textform/__init__.py
textform/add.py
textform/capture.py
textform/cast.py
textform/common.py
textform/copy.py
textform/divide.py
textform/drop.py
textform/fill.py
textform/fold.py
textform/format.py
textform/iterate.py
textform/lag.py
textform/lift.py
textform/limit.py
textform/lookup.py
textform/match.py
textform/merge.py
textform/nest.py
textform/project.py
textform/read.py
textform/replace.py
textform/select.py
textform/sequence.py
textform/split.py
textform/text.py
textform/transform.py
textform/unfold.py
textform/unnest.py
textform/write.py
textform/layouts/__init__.py
textform/layouts/csv.py
textform/layouts/dictreader.py
textform/layouts/factory.py
textform/layouts/iterators.py
textform/layouts/json.py
textform/layouts/jsonl.py
textform/layouts/md.py
textform/layouts/rst.py
textform/layouts/text.py
textform-0.11.0.dist-info/LICENSE
textform-0.11.0.dist-info/METADATA
textform-0.11.0.dist-info/WHEEL
textform-0.11.0.dist-info/top_level.txt
textform-0.11.0.dist-info/RECORD
