Metadata-Version: 2.1
Name: textform
Version: 0.11.0
Summary: A text shaping package.
Home-page: https://github.com/hawkfish/textform
Author: Richard Wesley
Author-email: hawkfish@electricfish.com
License: UNKNOWN
Project-URL: Bug Tracker, https://github.com/hawkfish/textform/issues
Platform: UNKNOWN
Classifier: Programming Language :: Python :: 3
Classifier: License :: OSI Approved :: MIT License
Classifier: Operating System :: OS Independent
Requires-Python: >=3.6
License-File: LICENSE
